{
  "project_info": {
    "project_number": "844944388061",
    "project_id": "zeljoprojekat",
    "storage_bucket": "zeljoprojekat.appspot.com"
  },
  "client": [
    {
      "client_info": {
        "mobilesdk_app_id": "1:844944388061:android:a07293a8935422d2419034",
        "android_client_info": {
          "package_name": "ba.example.zeljoprojekat"
        }
      },
      "oauth_client": [
        {
          "client_id": "844944388061-go58nbf49bmfrigp17sb6kj3at9v36n3.apps.googleusercontent.com",
          "client_type": 3
        }
      ],
      "api_key": [
        {
          "current_key": "AIzaSyCb1WbQ6rMbriBqu1lGHbVa_a1Ij4MtdW4"
        }
      ],
      "services": {
        "appinvite_service": {
          "other_platform_oauth_client": [
            {
              "client_id": "844944388061-go58nbf49bmfrigp17sb6kj3at9v36n3.apps.googleusercontent.com",
              "client_type": 3
            }
          ]
        }
      }
    }
  ],
  "configuration_version": "1"
}